tyler/__init__.py
tyler/config.py
tyler/a2a/__init__.py
tyler/a2a/adapter.py
tyler/a2a/client.py
tyler/a2a/notifications.py
tyler/a2a/server.py
tyler/a2a/types.py
tyler/cli/__init__.py
tyler/cli/chat.py
tyler/cli/init.py
tyler/cli/main.py
tyler/eval/__init__.py
tyler/eval/agent_eval.py
tyler/eval/conversations.py
tyler/eval/expectations.py
tyler/eval/mock_tools.py
tyler/eval/results.py
tyler/eval/scorers.py
tyler/mcp/__init__.py
tyler/mcp/config_loader.py
tyler/models/__init__.py
tyler/models/agent.py
tyler/models/completion_handler.py
tyler/models/execution.py
tyler/models/message_factory.py
tyler/models/retry_config.py
tyler/models/tool_call.py
tyler/models/tool_manager.py
tyler/streaming/__init__.py
tyler/streaming/base.py
tyler/streaming/core.py
tyler/streaming/events.py
tyler/streaming/openai.py
tyler/streaming/vercel.py
tyler/streaming/vercel_objects.py
tyler/streaming/vercel_protocol.py
tyler/utils/__init__.py
tyler/utils/files.py
tyler/utils/logging.py
tyler/utils/tool_runner.py
tyler/utils/tool_strategies.py
slide_tyler-6.3.0.dist-info/METADATA
slide_tyler-6.3.0.dist-info/WHEEL
slide_tyler-6.3.0.dist-info/entry_points.txt
slide_tyler-6.3.0.dist-info/licenses/LICENSE
slide_tyler-6.3.0.dist-info/RECORD
