Metadata-Version: 2.4
Name: slide-tyler
Version: 6.3.0
Summary: Tyler: A development kit for manifesting AI agents with a complete lack of conventional limitations
Project-URL: Homepage, https://github.com/adamwdraper/slide
Project-URL: Documentation, https://github.com/adamwdraper/slide#readme
Project-URL: Repository, https://github.com/adamwdraper/slide
Project-URL: Bug Tracker, https://github.com/adamwdraper/slide/issues
Author: adamwdraper
License: MIT
License-File: LICENSE
Classifier: Development Status :: 3 - Alpha
Classifier: Intended Audience :: Developers
Classifier: License :: OSI Approved :: MIT License
Classifier: Operating System :: OS Independent
Classifier: Programming Language :: Python :: 3
Classifier: Programming Language :: Python :: 3.11
Classifier: Programming Language :: Python :: 3.12
Classifier: Programming Language :: Python :: 3.13
Requires-Python: >=3.11
Requires-Dist: a2a-sdk>=0.3.0
Requires-Dist: aiohappyeyeballs>=2.4.4
Requires-Dist: aiohttp>=3.11.11
Requires-Dist: aiosignal>=1.3.2
Requires-Dist: aiosqlite>=0.21.0
Requires-Dist: alembic>=1.14.1
Requires-Dist: annotated-types>=0.7.0
Requires-Dist: anyio>=4.7.0
Requires-Dist: apscheduler>=3.11.0
Requires-Dist: asyncpg>=0.30.0
Requires-Dist: attrs>=24.3.0
Requires-Dist: backoff>=2.2.1
Requires-Dist: beautifulsoup4>=4.12.0
Requires-Dist: blinker>=1.9.0
Requires-Dist: browser-use>=0.1.40
Requires-Dist: cachetools>=5.5.0
Requires-Dist: click>=8.1.8
Requires-Dist: distro>=1.9.0
Requires-Dist: docker-pycreds>=0.4.0
Requires-Dist: email-validator>=2.2.0
Requires-Dist: emoji>=2.14.0
Requires-Dist: fastapi>=0.115.0
Requires-Dist: filelock>=3.16.1
Requires-Dist: filetype>=1.2.0
Requires-Dist: flask>=3.1.0
Requires-Dist: frozenlist>=1.5.0
Requires-Dist: fsspec>=2024.12.0
Requires-Dist: gitdb>=4.0.11
Requires-Dist: gitpython>=3.1.43
Requires-Dist: gql>=3.5.0
Requires-Dist: graphql-core>=3.2.5
Requires-Dist: greenlet>=3.1.1
Requires-Dist: h11>=0.14.0
Requires-Dist: httpcore>=1.0.7
Requires-Dist: httpx>=0.27.2
Requires-Dist: huggingface-hub>=0.27.0
Requires-Dist: imap-tools>=1.9.0
Requires-Dist: importlib-metadata>=8.5.0
Requires-Dist: iniconfig>=2.0.0
Requires-Dist: itsdangerous>=2.2.0
Requires-Dist: jinja2>=3.1.5
Requires-Dist: jiter>=0.8.2
Requires-Dist: jsonschema-specifications>=2024.10.1
Requires-Dist: jsonschema>=4.23.0
Requires-Dist: litellm>=1.81.0
Requires-Dist: mako>=1.3.9
Requires-Dist: markdown-it-py>=3.0.0
Requires-Dist: markupsafe>=3.0.2
Requires-Dist: mcp>=1.25.0
Requires-Dist: mdurl>=0.1.2
Requires-Dist: multidict>=6.1.0
Requires-Dist: narwhals>=1.19.1
Requires-Dist: numpy>=2.2.1
Requires-Dist: openai>=2.15.0
Requires-Dist: packaging>=24.2
Requires-Dist: pandas>=2.2.3
Requires-Dist: pdf2image>=1.17.0
Requires-Dist: pillow>=11.0.0
Requires-Dist: platformdirs>=4.3.6
Requires-Dist: propcache>=0.2.1
Requires-Dist: protobuf>=5.29.2
Requires-Dist: psutil>=6.1.1
Requires-Dist: pyarrow>=18.1.0
Requires-Dist: pydantic-core>=2.27.2
Requires-Dist: pydantic>=2.10.4
Requires-Dist: pygments>=2.18.0
Requires-Dist: pypdf>=5.3.0
Requires-Dist: python-dateutil>=2.9.0.post0
Requires-Dist: python-dotenv>=1.0.1
Requires-Dist: pytz>=2024.2
Requires-Dist: pyyaml>=6.0.2
Requires-Dist: referencing>=0.35.1
Requires-Dist: regex>=2024.11.6
Requires-Dist: requests-toolbelt>=1.0.0
Requires-Dist: requests>=2.32.3
Requires-Dist: rich>=13.9.4
Requires-Dist: rpds-py>=0.22.3
Requires-Dist: sentry-sdk>=2.19.2
Requires-Dist: setproctitle>=1.3.4
Requires-Dist: six>=1.17.0
Requires-Dist: slack-sdk>=3.34.0
Requires-Dist: slide-lye>=6.3.0
Requires-Dist: slide-narrator>=6.3.0
Requires-Dist: smmap>=5.0.1
Requires-Dist: sniffio>=1.3.1
Requires-Dist: soupsieve>=2.6
Requires-Dist: sqlalchemy>=2.0.36
Requires-Dist: starlette>=0.41.3
Requires-Dist: tenacity>=9.0.0
Requires-Dist: tiktoken>=0.8.0
Requires-Dist: tokenizers>=0.21.0
Requires-Dist: toml>=0.10.2
Requires-Dist: tornado>=6.4.2
Requires-Dist: tqdm>=4.67.1
Requires-Dist: typing-extensions>=4.12.2
Requires-Dist: tzdata>=2024.2
Requires-Dist: urllib3>=2.3.0
Requires-Dist: uuid-utils>=0.10.0
Requires-Dist: uvicorn>=0.34.0
Requires-Dist: wandb>=0.19.1
Requires-Dist: weave>=0.52.24
Requires-Dist: werkzeug>=3.1.3
Requires-Dist: yarl>=1.18.3
Requires-Dist: zipp>=3.21.0
Provides-Extra: dev
Requires-Dist: coverage>=7.6.10; extra == 'dev'
Requires-Dist: pip-tools>=7.4.1; extra == 'dev'
Requires-Dist: pipdeptree>=2.25.0; extra == 'dev'
Requires-Dist: pytest-asyncio>=0.25.2; extra == 'dev'
Requires-Dist: pytest-cov>=6.0.0; extra == 'dev'
Requires-Dist: pytest>=8.3.4; extra == 'dev'
